spylind/__init__.py
spylind/_version.py
spylind/spyIVP.py
spylind/spylind.py
spylind/spylind_test.py
spylind/tests/__init__.py
spylind/tests/conftest.py
spylind/tests/spyIVP_test.py
spylind/tests/test_examples.py
spylind-0.1.dist-info/AUTHORS.rst
spylind-0.1.dist-info/LICENSE
spylind-0.1.dist-info/METADATA
spylind-0.1.dist-info/WHEEL
spylind-0.1.dist-info/entry_points.txt
spylind-0.1.dist-info/top_level.txt
spylind-0.1.dist-info/RECORD
