Metadata-Version: 2.1
Name: spylind
Version: 0.1
Summary: Simple definition and fast solution of quantum systems described by a Lindblad master equation.
Home-page: https://github.com/morgatron/spylind
Author: Morgan Hedges
Author-email: morgan.hedges@gmail.com
License: BSD (3-clause)
Platform: UNKNOWN
Classifier: Development Status :: 2 - Pre-Alpha
Classifier: Natural Language :: English
Classifier: Programming Language :: Python :: 3
Requires-Python: >=3.6
Requires-Dist: tensorflow (<2.3,>=2.1)
Requires-Dist: numpy
Requires-Dist: scipy
Requires-Dist: sympy
Requires-Dist: munch
Requires-Dist: qutip
